{"cameraMode":{"drawMode":0,"name":"Shaded","section":"Shading Mode"},"sceneLighting":true,"audioPlay":false,"sceneViewState":{"showFog":true,"showMaterialUpdate":false,"showSkybox":true,"showFlares":true,"showImageEffects":true,"showParticleSystems":true},"in2DMode":false,"pivot":{"x":-2.9088683128356935,"y":-1.8431684970855713,"z":1.207200527191162},"rotation":{"x":-0.24537310004234315,"y":0.41138699650764468,"z":-0.11592010408639908,"w":-0.8701782822608948},"size":6.605440139770508,"orthographic":false}